[{"Person": "Иван Попов", "Phone": "84956674328", "Birthday": "01.01.2000", "Email": "ivan@popov.ru", "Address": "Ленина, 165"}, {"Person": "Антор Николаев", "Phone": "84956674328", "Birthday": "01.01.1995", "Email": "anton@nikolaev.ru", "Address": "Пролетарская, 12"}, {"Person": "Мария Гаврилова", "Phone": "744-744", "Birthday": "01-02-1986", "Email": "semenova@mail.ru", "Address": "Пушкинская 1"}, {"Person": "Спиридонова Юлия", "Phone": "+7923423124", "Birthday": "01.05.1990", "Email": "tr@mail.ru", "Address": "Красная, 156"}, {"Person": "Максимилиан Юлий-Ивановский", "Phone": "+7 (911) 456-78-66", "Birthday": "01.09.2022", "Email": "sgpt@myandex.ru", "Address": "Москва, Будапештская, 176"}]